ggmail/__init__.py
ggmail/account.py
ggmail/authentication.py
ggmail/exception.py
ggmail/flag.py
ggmail/mailbox.py
ggmail/message.py
ggmail/policy.py
ggmail/utf7.py
ggmail-0.4.1.dist-info/LICENSE
ggmail-0.4.1.dist-info/WHEEL
ggmail-0.4.1.dist-info/METADATA
ggmail-0.4.1.dist-info/RECORD
