Metadata-Version: 2.1
Name: ggmail
Version: 0.4.1
Summary: Manage gmail account using python, forget about imap and just code what you supposed to do.
Home-page: https://github.com/dylandoamaral/ggmail
License: MIT
Keywords: python,library,simple,imap,human,pydantic
Author: dylandoamaral
Author-email: do.amaral.dylan@gmail.com
Requires-Python: >=3.7,<4
Classifier: License :: OSI Approved :: MIT License
Classifier: Programming Language :: Python :: 3
Classifier: Programming Language :: Python :: 3.7
Classifier: Programming Language :: Python :: 3.8
Classifier: Programming Language :: Python :: 3.9
Classifier: Programming Language :: Python :: 3.10
Classifier: Topic :: Software Development :: Libraries :: Python Modules
Requires-Dist: pydantic (>=1.10.2,<2.0.0)
Project-URL: Documentation, https://github.com/dylandoamaral/ggmail/wiki
Project-URL: Repository, https://github.com/dylandoamaral/ggmail
